azure/mgmt/keyvault/__init__.py
azure/mgmt/keyvault/_configuration.py
azure/mgmt/keyvault/_key_vault_management_client.py
azure/mgmt/keyvault/_serialization.py
azure/mgmt/keyvault/_version.py
azure/mgmt/keyvault/models.py
azure/mgmt/keyvault/py.typed
azure/mgmt/keyvault/aio/__init__.py
azure/mgmt/keyvault/aio/_configuration.py
azure/mgmt/keyvault/aio/_key_vault_management_client.py
azure/mgmt/keyvault/v2016_10_01/__init__.py
azure/mgmt/keyvault/v2016_10_01/_configuration.py
azure/mgmt/keyvault/v2016_10_01/_key_vault_management_client.py
azure/mgmt/keyvault/v2016_10_01/_patch.py
azure/mgmt/keyvault/v2016_10_01/_version.py
azure/mgmt/keyvault/v2016_10_01/py.typed
azure/mgmt/keyvault/v2016_10_01/aio/__init__.py
azure/mgmt/keyvault/v2016_10_01/aio/_configuration.py
azure/mgmt/keyvault/v2016_10_01/aio/_key_vault_management_client.py
azure/mgmt/keyvault/v2016_10_01/aio/_patch.py
azure/mgmt/keyvault/v2016_10_01/aio/operations/__init__.py
azure/mgmt/keyvault/v2016_10_01/aio/operations/_operations.py
azure/mgmt/keyvault/v2016_10_01/aio/operations/_patch.py
azure/mgmt/keyvault/v2016_10_01/aio/operations/_vaults_operations.py
azure/mgmt/keyvault/v2016_10_01/models/__init__.py
azure/mgmt/keyvault/v2016_10_01/models/_key_vault_management_client_enums.py
azure/mgmt/keyvault/v2016_10_01/models/_models_py3.py
azure/mgmt/keyvault/v2016_10_01/models/_patch.py
azure/mgmt/keyvault/v2016_10_01/operations/__init__.py
azure/mgmt/keyvault/v2016_10_01/operations/_operations.py
azure/mgmt/keyvault/v2016_10_01/operations/_patch.py
azure/mgmt/keyvault/v2016_10_01/operations/_vaults_operations.py
azure/mgmt/keyvault/v2018_02_14/__init__.py
azure/mgmt/keyvault/v2018_02_14/_configuration.py
azure/mgmt/keyvault/v2018_02_14/_key_vault_management_client.py
azure/mgmt/keyvault/v2018_02_14/_patch.py
azure/mgmt/keyvault/v2018_02_14/_version.py
azure/mgmt/keyvault/v2018_02_14/py.typed
azure/mgmt/keyvault/v2018_02_14/aio/__init__.py
azure/mgmt/keyvault/v2018_02_14/aio/_configuration.py
azure_mgmt_keyvault-10.3.1.dist-info/LICENSE
azure_mgmt_keyvault-10.3.1.dist-info/METADATA
azure_mgmt_keyvault-10.3.1.dist-info/WHEEL
azure_mgmt_keyvault-10.3.1.dist-info/top_level.txt
azure_mgmt_keyvault-10.3.1.dist-info/RECORD
